pyfermions/__init__.py
pyfermions/hilbert.py
pyfermions/mera.py
pyfermions/signal.py
pyfermions/test_hilbert.py
pyfermions/test_signal.py
pyfermions/test_utils.py
pyfermions/test_wavelets.py
pyfermions/utils.py
pyfermions/wavelets.py
pyfermions-1.4.dist-info/LICENSE
pyfermions-1.4.dist-info/METADATA
pyfermions-1.4.dist-info/WHEEL
pyfermions-1.4.dist-info/top_level.txt
pyfermions-1.4.dist-info/RECORD
