Metadata-Version: 2.1
Name: pyfermions
Version: 1.4
Summary: Rigorous free fermion entanglement renormalization from wavelet theory
Home-page: https://github.com/qi-rub/pyfermions
Maintainer: Michael Walter
Maintainer-email: michael.walter@gmail.com
License: MIT
Classifier: Development Status :: 3 - Alpha
Classifier: Intended Audience :: Science/Research
Classifier: License :: OSI Approved :: MIT License
Classifier: Programming Language :: Python :: 3 :: Only
Classifier: Topic :: Scientific/Engineering :: Physics
Classifier: Topic :: Scientific/Engineering :: Mathematics
License-File: LICENSE
Requires-Dist: matplotlib
Requires-Dist: numpy
Requires-Dist: scipy
Requires-Dist: pandas
Requires-Dist: jupyter
Provides-Extra: dev
Requires-Dist: pytest ; extra == 'dev'
Requires-Dist: wheel ; extra == 'dev'
Requires-Dist: black ; extra == 'dev'
Requires-Dist: twine ; extra == 'dev'
Requires-Dist: jupyter-contrib-nbextensions ; extra == 'dev'
